{
  "type": "minecraft:block",
  "pools": [
    {
      "bonus_rolls": 0.0,
      "entries": [
        {
          "type": "minecraft:alternatives",
          "children": [
            {
              "type": "minecraft:item",
              "conditions": [
                {
                  "condition": "minecraft:match_tool",
                  "predicate": {
                    "enchantments": [
                      {
                        "enchantment": "minecraft:silk_touch",
                        "levels": {
                          "min": 1
                        }
                      }
                    ]
                  }
                }
              ],
              "name": "misc_twf:white_trash_bag"
            },
            {
              "type": "minecraft:loot_table",
              "conditions": [
                {
                  "condition": "minecraft:survives_explosion"
                }
              ],
              "name": "minecraft:gameplay/fishing/junk"
            }
          ]
        }
      ],
      "rolls": 1.0
    }
  ]
}